LICENSE
README.md
setup.py
newsi/__init__.py
newsi/newsi.py
newsi.egg-info/PKG-INFO
newsi.egg-info/SOURCES.txt
newsi.egg-info/dependency_links.txt
newsi.egg-info/requires.txt
newsi.egg-info/top_level.txt