Metadata-Version: 2.1
Name: newsi
Version: 0.0.3
Summary: Newsi is Free News API is able to fetch local news and category news in real time.
Home-page: UNKNOWN
Author: Mohammed Alaa Zaki
Author-email: <mohammedalaazakitayyem@gmail.com>
License: UNKNOWN
Keywords: python,news api,free news api,newsi,python free news api,rapidapi,news feed api,google news api,best news api,python news api,python news library,python news package,breaking news api,google news api free,news api for python,news library for python
Platform: UNKNOWN
Classifier: Development Status :: 1 - Planning
Classifier: Intended Audience :: Developers
Classifier: Programming Language :: Python :: 3
Classifier: Operating System :: Unix
Classifier: Operating System :: MacOS :: MacOS X
Classifier: Operating System :: Microsoft :: Windows
License-File: LICENSE
